pysatl/__init__.py
pysatl/apdu_tool.py
pysatl-1.2.6.dist-info/LICENSE
pysatl-1.2.6.dist-info/METADATA
pysatl-1.2.6.dist-info/WHEEL
pysatl-1.2.6.dist-info/top_level.txt
pysatl-1.2.6.dist-info/RECORD
