Metadata-Version: 2.1
Name: pysatl
Version: 1.2.6
Summary: Library to transport ISO7816-4 APDUs over anything
Home-page: https://github.com/sebastien-riou/SATL
Author: Sebastien Riou
Author-email: matic@nimp.co.uk
License: UNKNOWN
Platform: UNKNOWN
Classifier: Programming Language :: Python :: 3
Classifier: License :: OSI Approved :: Apache Software License
Classifier: Operating System :: OS Independent
Classifier: Development Status :: 5 - Production/Stable
Requires-Python: >=3.6
